{
  "resourceType": "StructureDefinition",
  "id": "consent-management-patient",
  "url": "http://utn/consentresource.com/StructureDefinition/consent-management-patient",
  "name": "ConsentManagementPatient",
  "title": "Consent Management: Patient",
  "status": "draft",
  "fhirVersion": "4.0.1",
  "kind": "resource",
  "abstract": false,
  "type": "Patient",
  "baseDefinition": "http://hl7.org/fhir/StructureDefinition/Patient",
  "derivation": "constraint",
  "differential": {
    "element": [
      {
        "id": "Patient.identifier",
        "extension": [
          {
            "url": "http://hl7.org/fhir/StructureDefinition/structuredefinition-standards-status",
            "valueCode": "normative"
          }
        ],
        "path": "Patient.identifier",
        "min": 1,
        "mustSupport": true
      },
      {
        "id": "Patient.identifier.type",
        "extension": [
          {
            "url": "http://hl7.org/fhir/StructureDefinition/structuredefinition-standards-status",
            "valueCode": "normative"
          }
        ],
        "path": "Patient.identifier.type",
        "min": 1,
        "mustSupport": true,
        "binding": {
          "strength": "extensible",
          "valueSet": "http://fhir.de/ConsentManagement/ValueSet/ContextIdentifierType"
        }
      },
      {
        "id": "Patient.identifier.type.coding",
        "extension": [
          {
            "url": "http://hl7.org/fhir/StructureDefinition/structuredefinition-standards-status",
            "valueCode": "normative"
          }
        ],
        "path": "Patient.identifier.type.coding",
        "min": 1,
        "mustSupport": true
      },
      {
        "id": "Patient.identifier.type.coding.system",
        "extension": [
          {
            "url": "http://hl7.org/fhir/StructureDefinition/structuredefinition-standards-status",
            "valueCode": "normative"
          }
        ],
        "path": "Patient.identifier.type.coding.system",
        "min": 1,
        "mustSupport": true
      },
      {
        "id": "Patient.identifier.type.coding.code",
        "extension": [
          {
            "url": "http://hl7.org/fhir/StructureDefinition/structuredefinition-standards-status",
            "valueCode": "normative"
          }
        ],
        "path": "Patient.identifier.type.coding.code",
        "min": 1,
        "mustSupport": true
      },
      {
        "id": "Patient.identifier.system",
        "extension": [
          {
            "url": "http://hl7.org/fhir/StructureDefinition/structuredefinition-standards-status",
            "valueCode": "normative"
          }
        ],
        "path": "Patient.identifier.system",
        "min": 1,
        "mustSupport": true
      },
      {
        "id": "Patient.identifier.value",
        "extension": [
          {
            "url": "http://hl7.org/fhir/StructureDefinition/structuredefinition-standards-status",
            "valueCode": "normative"
          }
        ],
        "path": "Patient.identifier.value",
        "min": 1,
        "mustSupport": true
      }
    ]
  }
}
